speedy/__init__.py
speedy/_parsers.py
speedy/application.py
speedy/background.py
speedy/concurrency.py
speedy/constants.py
speedy/enums.py
speedy/status_code.py
speedy/connection/__init__.py
speedy/connection/base.py
speedy/connection/request.py
speedy/connection/websockets.py
speedy/datastructures/__init__.py
speedy/datastructures/cookie.py
speedy/datastructures/headers.py
speedy/datastructures/multi_dicts.py
speedy/datastructures/secrets_values.py
speedy/datastructures/state.py
speedy/datastructures/upload_file.py
speedy/datastructures/url.py
speedy/datastructures/websocket.py
speedy/endpoints/__init__.py
speedy/endpoints/http_endpoint.py
speedy/endpoints/websoket_endpoint.py
speedy/exceptions/__init__.py
speedy/exceptions/base.py
speedy/exceptions/http_exceptions.py
speedy/exceptions/websocket.py
speedy/exceptions/websocket_exceptions.py
speedy/middleware/__init__.py
speedy/middleware/base.py
speedy/middleware/errors.py
speedy/protocols/__init__.py
speedy/protocols/app_logs.py
speedy/protocols/application.py
speedy/protocols/background.py
speedy/protocols/endpoints.py
speedy/protocols/http_connect.py
speedy/protocols/methods.py
speedy/protocols/middleware.py
speedy/protocols/request.py
speedy/protocols/response.py
speedy/protocols/routing.py
speedy/protocols/secrets_values.py
speedy/protocols/websockets.py
speedy/response/__init__.py
speedy/response/base.py
speedy/response/html.py
speedy/response/json.py
speedy/response/plaint_text.py
speedy/types/__init__.py
speedy/types/application.py
speedy/types/application_types.py
speedy/types/asgi_types.py
speedy/utils/__init__.py
speedy/utils/helpers.py
speedy/utils/predicates.py
speedy/utils/sync.py
SpeedApi-0.0.1.dist-info/LICENSE
SpeedApi-0.0.1.dist-info/METADATA
SpeedApi-0.0.1.dist-info/WHEEL
SpeedApi-0.0.1.dist-info/top_level.txt
SpeedApi-0.0.1.dist-info/RECORD
