Metadata-Version: 2.1
Name: SpeedApi
Version: 0.0.1
Summary: In development
Author-email: Alexander Kuzmin <qrer71@yandex.ru>, Alexander Kuzmin <funks.1@yandex.ru>
License: MIT License
Project-URL: Homepage, https://github.com/WolfMTK/speedy
Project-URL: Repository, https://github.com/WolfMTK/speedy
Classifier: Programming Language :: Python :: 3
Classifier: Programming Language :: Python :: 3.12
Classifier: Intended Audience :: Developers
Classifier: License :: OSI Approved :: MIT License
Classifier: Operating System :: OS Independent
Requires-Python: >=3.12
License-File: LICENSE
Requires-Dist: multidict <=6.0.5
Provides-Extra: dev
Requires-Dist: covdefaults ; extra == 'dev'
Requires-Dist: pytest <=8.2.1 ; extra == 'dev'
Requires-Dist: ujson <=5.10.0 ; extra == 'dev'
Requires-Dist: orjson <=3.10.3 ; extra == 'dev'
Requires-Dist: httpx <=0.27.0 ; extra == 'dev'
Requires-Dist: pytest-cov ; extra == 'dev'
Provides-Extra: orjson
Requires-Dist: orjson <=3.10.3 ; extra == 'orjson'
Provides-Extra: ujson
Requires-Dist: ujson <=5.10.0 ; extra == 'ujson'
